{
  "project_info": {
    "project_number": "1004176470493",
    "project_id": "nzni-5b945",
    "storage_bucket": "nzni-5b945.firebasestorage.app"
  },
  "client": [
    {
      "client_info": {
        "mobilesdk_app_id": "1:1004176470493:android:e0df80f99aba7e510c0634",
        "android_client_info": {
          "package_name": "com.example.socmedapp"
        }
      },
      "oauth_client": [],
      "api_key": [
        {
          "current_key": "AIzaSyCQeNAi2lGBoVNhPikTyEKTEvLY30-RKjI"
        }
      ],
      "services": {
        "appinvite_service": {
          "other_platform_oauth_client": []
        }
      }
    }
  ],
  "configuration_version": "1"
}